robotooter/__init__.py
robotooter/base_creator.py
robotooter/bots/__init__.py
robotooter/bots/base_bot.py
robotooter/bots/markov/__init__.py
robotooter/bots/markov/markov_bot.py
robotooter/bots/markov/markov_creator.py
robotooter/bots/markov/markov_processor.py
robotooter/cli/__init__.py
robotooter/cli/authorize.py
robotooter/cli/cli.py
robotooter/cli/configure.py
robotooter/cli/create_bot.py
robotooter/cli/info.py
robotooter/cli/util.py
robotooter/file_filter.py
robotooter/filters/__init__.py
robotooter/filters/base_filter.py
robotooter/filters/blank_line.py
robotooter/filters/gutenberg.py
robotooter/filters/paragraph_combining.py
robotooter/mastodon/__init__.py
robotooter/mastodon/authenticator.py
robotooter/mastodon/manager.py
robotooter/mastodon/mixin.py
robotooter/mixins/__init__.py
robotooter/mixins/resources.py
robotooter/mocks/__init__.py
robotooter/mocks/fake_bot.py
robotooter/mocks/fake_client.py
robotooter/models/__init__.py
robotooter/models/configs.py
robotooter/models/saveable_model.py
robotooter/models/statuses.py
robotooter/plugins/__init__.py
robotooter/plugins/base_plugin.py
robotooter/py.typed
robotooter/rt.py
robotooter/stubs/robotooter/__init__.pyi
robotooter/stubs/robotooter/base_creator.pyi
robotooter/stubs/robotooter/bots/__init__.pyi
robotooter/stubs/robotooter/bots/base_bot.pyi
robotooter/stubs/robotooter/bots/markov/__init__.pyi
robotooter/stubs/robotooter/bots/markov/markov_bot.pyi
robotooter/stubs/robotooter/bots/markov/markov_creator.pyi
robotooter/stubs/robotooter/bots/markov/markov_processor.pyi
robotooter/stubs/robotooter/cli/__init__.pyi
robotooter/stubs/robotooter/cli/authorize.pyi
robotooter/stubs/robotooter/cli/cli.pyi
robotooter/stubs/robotooter/cli/configure.pyi
robotooter/stubs/robotooter/cli/create_bot.pyi
robotooter/stubs/robotooter/cli/info.pyi
robotooter/stubs/robotooter/cli/util.pyi
robotooter/stubs/robotooter/file_filter.pyi
robotooter/stubs/robotooter/filters/__init__.pyi
robotooter-0.4.0.dist-info/LICENSE
robotooter-0.4.0.dist-info/METADATA
robotooter-0.4.0.dist-info/WHEEL
robotooter-0.4.0.dist-info/entry_points.txt
robotooter-0.4.0.dist-info/RECORD
