Metadata-Version: 2.1
Name: robotooter
Version: 0.4.0
Summary: A Python framework for easily creating Mastodon bots with pluggable content generation and filtering capabilities
Home-page: https://codeberg.org/bfordham/robotooter
License: AGPL-3.0
Keywords: mastodon,bot,social-media,markov,automation
Author: Bryan L. Fordham
Author-email: bfordham@naughtybaptist.com
Requires-Python: >=3.12,<4.0
Classifier: Development Status :: 3 - Alpha
Classifier: Intended Audience :: Developers
Classifier: License :: OSI Approved :: GNU Affero General Public License v3
Classifier: Operating System :: OS Independent
Classifier: Programming Language :: Python :: 3
Classifier: Programming Language :: Python :: 3.12
Classifier: Topic :: Communications :: Chat
Classifier: Topic :: Internet :: WWW/HTTP :: Dynamic Content
Classifier: Topic :: Software Development :: Libraries :: Python Modules
Requires-Dist: jinja2 (>=3.1.6,<4.0.0)
Requires-Dist: markovify (>=0.9.4,<0.10.0)
Requires-Dist: mastodon-py (>=2.0.1,<3.0.0)
Requires-Dist: pydantic (>=2.11.7,<3.0.0)
Requires-Dist: requests (>=2.32.4,<3.0.0)
Project-URL: Documentation, https://codeberg.org/bfordham/robotooter#readme
Project-URL: Repository, https://codeberg.org/bfordham/robotooter
